MANIFEST.in
README.rst
setup.py
docs/HISTORY.rst
docs/LICENSE.GPL
docs/LICENSE.txt
seantis/__init__.py
seantis.agencies.egg-info/PKG-INFO
seantis.agencies.egg-info/SOURCES.txt
seantis.agencies.egg-info/dependency_links.txt
seantis.agencies.egg-info/entry_points.txt
seantis.agencies.egg-info/namespace_packages.txt
seantis.agencies.egg-info/not-zip-safe
seantis.agencies.egg-info/requires.txt
seantis.agencies.egg-info/top_level.txt
seantis/agencies/__init__.py
seantis/agencies/configure.zcml
seantis/agencies/events.py
seantis/agencies/events.zcml
seantis/agencies/interfaces.py
seantis/agencies/maintenance.py
seantis/agencies/profiles.zcml
seantis/agencies/setuphandler.py
seantis/agencies/sync.sh
seantis/agencies/testing.py
seantis/agencies/upgrades.py
seantis/agencies/upgrades.zcml
seantis/agencies/browser/__init__.py
seantis/agencies/browser/base.py
seantis/agencies/browser/configure.zcml
seantis/agencies/browser/macros.py
seantis/agencies/browser/membership.py
seantis/agencies/browser/organization.py
seantis/agencies/browser/pdfexport.py
seantis/agencies/browser/renderer.py
seantis/agencies/browser/xlsexport.py
seantis/agencies/browser/xlsimport.py
seantis/agencies/browser/templates/macros.pt
seantis/agencies/browser/templates/membership.pt
seantis/agencies/browser/templates/organization.pt
seantis/agencies/locales/manual.pot
seantis/agencies/locales/seantis.agencies.pot
seantis/agencies/locales/de/LC_MESSAGES/plone.po
seantis/agencies/locales/de/LC_MESSAGES/seantis.agencies.po
seantis/agencies/locales/de/LC_MESSAGES/seantis.people.po
seantis/agencies/profiles/default/actions.xml
seantis/agencies/profiles/default/browserlayer.xml
seantis/agencies/profiles/default/metadata.xml
seantis/agencies/profiles/default/seantis.agencies-default.txt
seantis/agencies/profiles/default/types.xml
seantis/agencies/profiles/default/types/seantis.agencies.member.xml
seantis/agencies/profiles/default/types/seantis.agencies.membership.xml
seantis/agencies/profiles/default/types/seantis.agencies.organization.xml
seantis/agencies/tests/__init__.py
seantis/agencies/tests/test_import_export.py
seantis/agencies/tests/test_pdf_export.py
seantis/agencies/tests/test_schema.py
seantis/agencies/types/__init__.py
seantis/agencies/types/member.xml