Metadata-Version: 1.1
Name: seantis.agencies
Version: 0.11.2
Summary: A directory of people for (government) agencies.
Home-page: https://github.com/seantis/seantis.agencies
Author: Seantis GmbH
Author-email: info@seantis.ch
License: GPLv2
Keywords: seantis.agencies plone
Platform: UNKNOWN
Classifier: Framework :: Plone
Classifier: Framework :: Plone :: 4.3
Classifier: Intended Audience :: Developers
Classifier: License :: OSI Approved :: GNU General Public License v2 (GPLv2)
Classifier: Natural Language :: English
Classifier: Programming Language :: Python :: 2.7
Classifier: Topic :: Software Development :: Libraries :: Python Modules
